components/__init__.py
components/data_ingestion.py
components/data_transformation.py
components/model_evaluation.py
components/model_tariner.py
dbautomater/__init__.py
dbautomater/mongo_crud.py
dbautomater-0.0.6.dist-info/licenses/LICENSE
exception/__init__.py
exception/exception.py
logger/__init__.py
logger/logger.py
pipeline/__init__.py
pipeline/prediction_pipeline.py
pipeline/training_pipeline.py
utils/__init__.py
utils/utils.py
dbautomater-0.0.6.dist-info/METADATA
dbautomater-0.0.6.dist-info/WHEEL
dbautomater-0.0.6.dist-info/top_level.txt
dbautomater-0.0.6.dist-info/RECORD
