Metadata-Version: 2.4
Name: dbautomater
Version: 0.0.6
Summary: while learning mlops I created this python package for connecting with database.
Home-page: https://github.com/mouryag/MLOPS-Project
Author: mouryag
Author-email: mouryag <mouryag99@gmail.com>
License: MIT
Project-URL: Repository, https://github.com/mouryag/MLOPS-Project
Project-URL: Bug Tracker, https://github.com/mouryag/MLOPS-Project/issues
Requires-Python: >=3.10
License-File: LICENSE
Requires-Dist: ensure==1.0.2
Requires-Dist: py-youtube==1.1.7
Dynamic: author
Dynamic: home-page
Dynamic: license-file
